.DS_Store
pandas_linker/__init__.py
pandas_linker/comparison.py
pandas_linker/linker.py
pandas_linker-0.0.2.dist-info/DESCRIPTION.rst
pandas_linker-0.0.2.dist-info/METADATA
pandas_linker-0.0.2.dist-info/RECORD
pandas_linker-0.0.2.dist-info/WHEEL
pandas_linker-0.0.2.dist-info/metadata.json
pandas_linker-0.0.2.dist-info/top_level.txt
