Metadata-Version: 2.0
Name: pandas-linker
Version: 0.0.2
Summary: Linking rows of pandas dataframes
Home-page: https://github.com/stefanw/pandas-linker
Author: Stefan Wehrmeyer
Author-email: mail@stefanwehrmeyer.com
License: MIT
Platform: UNKNOWN
Classifier: Development Status :: 4 - Beta
Classifier: Intended Audience :: Science/Research
Classifier: License :: OSI Approved :: MIT License
Classifier: Natural Language :: English
Classifier: Operating System :: OS Independent
Classifier: Programming Language :: Python :: 2.7
Classifier: Programming Language :: Python :: 3.5
Classifier: Topic :: Scientific/Engineering
Requires-Dist: pandas
Requires-Dist: pyprind
